{
    "root": "/home/thebesttv/libav",
    "compile_commands": "/home/thebesttv/libav/compile_commands.json",
    "docker": "thebesttv/vul-manual:710b0e",
    "results": [
        {
            "type": "npe",
            "locations": [
                {
                    "type": "source",
                    "file": "/home/thebesttv/libav/libavutil/mem.c",
                    "line": 63,
                    "column": 11
                },
                {
                    "type": "stmt",
                    "file": "/home/thebesttv/libav/libavutil/mem.c",
                    "line": 113,
                    "column": 5
                },
                {
                    "type": "stmt",
                    "file": "/home/thebesttv/libav/libavutil/mem.c",
                    "line": 186,
                    "column": 5
                },
                {
                    "type": "stmt",
                    "file": "/home/thebesttv/libav/libavutil/mem.c",
                    "line": 189,
                    "column": 5
                },
                {
                    "type": "stmt",
                    "file": "/home/thebesttv/libav/libavcodec/smacker.c",
                    "line": 193,
                    "column": 5
                },
                {
                    "type": "stmt",
                    "file": "/home/thebesttv/libav/libavcodec/smacker.c",
                    "line": 205,
                    "column": 9
                },
                {
                    "type": "stmt",
                    "file": "/home/thebesttv/libav/libavcodec/smacker.c",
                    "line": 100,
                    "column": 5
                },
                {
                    "type": "sink",
                    "file": "/home/thebesttv/libav/libavcodec/smacker.c",
                    "line": 106,
                    "column": 13
                }
            ]
        },
        {
            "type": "npe",
            "locations": [
                {
                    "type": "source",
                    "file": "/home/thebesttv/libav/libavutil/mem.c",
                    "line": 63,
                    "column": 11
                },
                {
                    "type": "stmt",
                    "file": "/home/thebesttv/libav/libavutil/mem.c",
                    "line": 113,
                    "column": 5
                },
                {
                    "type": "stmt",
                    "file": "/home/thebesttv/libav/libavutil/mem.c",
                    "line": 186,
                    "column": 5
                },
                {
                    "type": "stmt",
                    "file": "/home/thebesttv/libav/libavutil/mem.c",
                    "line": 189,
                    "column": 5
                },
                {
                    "type": "stmt",
                    "file": "/home/thebesttv/libav/libavcodec/smacker.c",
                    "line": 194,
                    "column": 5
                },
                {
                    "type": "stmt",
                    "file": "/home/thebesttv/libav/libavcodec/smacker.c",
                    "line": 205,
                    "column": 9
                },
                {
                    "type": "stmt",
                    "file": "/home/thebesttv/libav/libavcodec/smacker.c",
                    "line": 100,
                    "column": 5
                },
                {
                    "type": "sink",
                    "file": "/home/thebesttv/libav/libavcodec/smacker.c",
                    "line": 107,
                    "column": 13
                }
            ]
        },
        {
            "type": "npe",
            "locations": [
                {
                    "type": "source",
                    "file": "/home/thebesttv/libav/libavutil/mem.c",
                    "line": 63,
                    "column": 11
                },
                {
                    "type": "stmt",
                    "file": "/home/thebesttv/libav/libavutil/mem.c",
                    "line": 113,
                    "column": 5
                },
                {
                    "type": "stmt",
                    "file": "/home/thebesttv/libav/libavutil/mem.c",
                    "line": 186,
                    "column": 5
                },
                {
                    "type": "stmt",
                    "file": "/home/thebesttv/libav/libavutil/mem.c",
                    "line": 189,
                    "column": 5
                },
                {
                    "type": "stmt",
                    "file": "/home/thebesttv/libav/libavcodec/smacker.c",
                    "line": 195,
                    "column": 5
                },
                {
                    "type": "stmt",
                    "file": "/home/thebesttv/libav/libavcodec/smacker.c",
                    "line": 205,
                    "column": 9
                },
                {
                    "type": "stmt",
                    "file": "/home/thebesttv/libav/libavcodec/smacker.c",
                    "line": 100,
                    "column": 5
                },
                {
                    "type": "sink",
                    "file": "/home/thebesttv/libav/libavcodec/smacker.c",
                    "line": 112,
                    "column": 9
                }
            ]
        },
        {
            "type": "npe",
            "locations": [
                {
                    "type": "source",
                    "file": "/home/thebesttv/libav/libavutil/mem.c",
                    "line": 63,
                    "column": 11
                },
                {
                    "type": "stmt",
                    "file": "/home/thebesttv/libav/libavutil/mem.c",
                    "line": 113,
                    "column": 5
                },
                {
                    "type": "stmt",
                    "file": "/home/thebesttv/libav/libavutil/mem.c",
                    "line": 186,
                    "column": 5
                },
                {
                    "type": "stmt",
                    "file": "/home/thebesttv/libav/libavutil/mem.c",
                    "line": 189,
                    "column": 5
                },
                {
                    "type": "stmt",
                    "file": "/home/thebesttv/libav/libavcodec/smacker.c",
                    "line": 200,
                    "column": 5
                },
                {
                    "type": "stmt",
                    "file": "/home/thebesttv/libav/libavcodec/smacker.c",
                    "line": 218,
                    "column": 9
                },
                {
                    "type": "stmt",
                    "file": "/home/thebesttv/libav/libavcodec/smacker.c",
                    "line": 100,
                    "column": 5
                },
                {
                    "type": "sink",
                    "file": "/home/thebesttv/libav/libavcodec/smacker.c",
                    "line": 106,
                    "column": 13
                }
            ]
        },
        {
            "type": "npe",
            "locations": [
                {
                    "type": "source",
                    "file": "/home/thebesttv/libav/libavutil/mem.c",
                    "line": 63,
                    "column": 11
                },
                {
                    "type": "stmt",
                    "file": "/home/thebesttv/libav/libavutil/mem.c",
                    "line": 113,
                    "column": 5
                },
                {
                    "type": "stmt",
                    "file": "/home/thebesttv/libav/libavutil/mem.c",
                    "line": 186,
                    "column": 5
                },
                {
                    "type": "stmt",
                    "file": "/home/thebesttv/libav/libavutil/mem.c",
                    "line": 189,
                    "column": 5
                },
                {
                    "type": "stmt",
                    "file": "/home/thebesttv/libav/libavcodec/smacker.c",
                    "line": 201,
                    "column": 5
                },
                {
                    "type": "stmt",
                    "file": "/home/thebesttv/libav/libavcodec/smacker.c",
                    "line": 218,
                    "column": 9
                },
                {
                    "type": "stmt",
                    "file": "/home/thebesttv/libav/libavcodec/smacker.c",
                    "line": 100,
                    "column": 5
                },
                {
                    "type": "sink",
                    "file": "/home/thebesttv/libav/libavcodec/smacker.c",
                    "line": 107,
                    "column": 13
                }
            ]
        },
        {
            "type": "npe",
            "locations": [
                {
                    "type": "source",
                    "file": "/home/thebesttv/libav/libavutil/mem.c",
                    "line": 63,
                    "column": 11
                },
                {
                    "type": "stmt",
                    "file": "/home/thebesttv/libav/libavutil/mem.c",
                    "line": 113,
                    "column": 5
                },
                {
                    "type": "stmt",
                    "file": "/home/thebesttv/libav/libavutil/mem.c",
                    "line": 186,
                    "column": 5
                },
                {
                    "type": "stmt",
                    "file": "/home/thebesttv/libav/libavutil/mem.c",
                    "line": 189,
                    "column": 5
                },
                {
                    "type": "stmt",
                    "file": "/home/thebesttv/libav/libavcodec/smacker.c",
                    "line": 202,
                    "column": 5
                },
                {
                    "type": "stmt",
                    "file": "/home/thebesttv/libav/libavcodec/smacker.c",
                    "line": 218,
                    "column": 9
                },
                {
                    "type": "stmt",
                    "file": "/home/thebesttv/libav/libavcodec/smacker.c",
                    "line": 100,
                    "column": 5
                },
                {
                    "type": "sink",
                    "file": "/home/thebesttv/libav/libavcodec/smacker.c",
                    "line": 112,
                    "column": 13
                }
            ]
        }
    ]
}
